cocobolo/__init__.py
cocobolo-0.0.1.dist-info/METADATA
cocobolo-0.0.1.dist-info/WHEEL
cocobolo-0.0.1.dist-info/top_level.txt
cocobolo-0.0.1.dist-info/RECORD
