Metadata-Version: 2.4
Name: cocobolo
Version: 0.0.1
Summary: MQTT message router
Author-email: Hans Gremmen <hans@leptonix.net>
License-Expression: MIT
Requires-Python: >=3.7
